business_metrics.py
Calculate_hw6-0.0.1.dist-info/METADATA
Calculate_hw6-0.0.1.dist-info/WHEEL
Calculate_hw6-0.0.1.dist-info/entry_points.txt
Calculate_hw6-0.0.1.dist-info/top_level.txt
Calculate_hw6-0.0.1.dist-info/RECORD
