Metadata-Version: 2.1
Name: Calculate_hw6
Version: 0.0.1
Summary: calculate roi
Author: Tornad06
Author-email: d.sadoyan@edu.centraluniversity.ru
Requires-Python: >=3.6
